Metadata-Version: 2.1
Name: python-mt-st
Version: 0.1.4
Summary: Module for controlling magnetic tape drives under Linux from Python
Home-page: https://github.com/twonote/python-mt-st
Author: hrchu
Author-email: petertc.chu@gmail.com
License: LGPLv2.1
Platform: UNKNOWN
Classifier: Programming Language :: Python :: 3
Classifier: License :: OSI Approved :: GNU Lesser General Public License v2 or later (LGPLv2+)
Classifier: Operating System :: POSIX :: Linux
Classifier: Topic :: System :: Archiving
Classifier: Topic :: System :: Hardware
Classifier: Topic :: System :: Systems Administration
Classifier: Topic :: Utilities
